LICENSE
MANIFEST.in
README.rst
setup.py
django_settings_list.egg-info/PKG-INFO
django_settings_list.egg-info/SOURCES.txt
django_settings_list.egg-info/dependency_links.txt
django_settings_list.egg-info/not-zip-safe
django_settings_list.egg-info/requires.txt
django_settings_list.egg-info/top_level.txt
settings_list/__init__.py
settings_list/views.py
settings_list/templates/admin/settings_list.html