Metadata-Version: 1.1
Name: django-settings-list
Version: 0.1.2
Summary: Django app that lists the settings values for a running project using a custom view accessible only by superusers.
Home-page: https://github.com/bryanchow/django-settings-list
Author: Bryan Chow
Author-email: UNKNOWN
License: WTFPL
Download-URL: https://github.com/bryanchow/django-settings-list/tarball/master
Platform: UNKNOWN
